setup.py
textland/__init__.py
textland/abc.py
textland/bits.py
textland/display.py
textland/drawing.py
textland/events.py
textland/image.py
textland/keys.py
textland.egg-info/PKG-INFO
textland.egg-info/SOURCES.txt
textland.egg-info/dependency_links.txt
textland.egg-info/top_level.txt