Metadata-Version: 1.0
Name: textland
Version: 0.1
Summary: Like wayland, for text apps
Home-page: https://github.com/zyga/textland
Author: Zygmunt Krynicki
Author-email: zygmunt.krynicki@canonical.com
License: GPLv3
Platform: UNKNOWN
